{
    "$schema": "https://raw.githubusercontent.com/jsonresume/resume-schema/master/schema.json",
    "basics": {
        "name": "홍길동",
        "label": "소프트웨어 개발자",
        "image": "/images/avatar-placeholder.svg",
        "imageStyle": "standard",
        "email": "user@example.com",
        "phone": "010-0000-0000",
        "url": "https://example.com",
        "summary": "Lorem ipsum dolor sit amet, consectetur adipiscing elit. Sed do eiusmod tempor incididunt ut labore et dolore magna aliqua.",
        "location": {
            "address": "서울특별시 중구 세종대로 110",
            "postalCode": "04500",
            "city": "서울",
            "countryCode": "KR",
            "region": "서울특별시"
        },
        "profiles": [
            {
                "network": "GitHub",
                "username": "username",
                "url": "https://github.com/username"
            }
        ]
    },
    "work": [
        {
            "name": "테크 회사",
            "position": "소프트웨어 개발자",
            "url": "https://example.com",
            "startDate": "2023-01-01",
            "endDate": "2024-12-01",
            "summary": "Lorem ipsum dolor sit amet, consectetur adipiscing elit. Proin gravida nibh vel velit auctor aliquet.",
            "highlights": [
                "Lorem ipsum dolor sit amet, consectetur adipiscing elit.",
                "Ut enim ad minim veniam, quis nostrud exercitation ullamco laboris."
            ],
            "jobField": "web"
        }
    ],
    "projects": [
        {
            "name": "샘플 웹 프로젝트",
            "startDate": "2024-06-01",
            "endDate": "2024-12-01",
            "description": "Lorem ipsum dolor sit amet, consectetur adipiscing elit. Sed do eiusmod tempor incididunt ut labore et dolore magna aliqua.",
            "highlights": [
                "Ut enim ad minim veniam, quis nostrud exercitation ullamco laboris.",
                "Duis aute irure dolor in reprehenderit in voluptate velit esse cillum dolore."
            ],
            "url": "https://example.com/",
            "jobField": "web"
        },
        {
            "name": "샘플 게임 프로젝트",
            "startDate": "2024-01-01",
            "endDate": "2024-05-01",
            "description": "Lorem ipsum dolor sit amet, consectetur adipiscing elit. Sed do eiusmod tempor incididunt ut labore et dolore magna aliqua.",
            "highlights": [
                "Ut enim ad minim veniam, quis nostrud exercitation ullamco laboris."
            ],
            "url": "https://example.com/game",
            "jobField": "game"
        }
    ],
    "education": [
        {
            "institution": "대학교",
            "url": "https://example.com/",
            "area": "소프트웨어 개발",
            "studyType": "학사",
            "startDate": "2011-01-01",
            "endDate": "2013-01-01",
            "score": "4.0",
            "courses": ["DB1101 - 기초 SQL"]
        }
    ],
    "awards": [
        {
            "title": "수상 내역",
            "date": "2014-11-01",
            "awarder": "발급 기관",
            "summary": "Lorem ipsum dolor sit amet, consectetur adipiscing elit. Aenean commodo ligula eget dolor."
        }
    ],
    "certificates": [
        {
            "name": "자격증",
            "date": "2021-11-07",
            "issuer": "발급 기관",
            "url": "https://example.com"
        }
    ],
    "skills": [
        {
            "name": "웹 개발",
            "level": "전문가",
            "keywords": ["HTML", "CSS", "JavaScript"]
        }
    ],
    "languages": [
        {
            "language": "한국어",
            "fluency": "모국어"
        },
        {
            "language": "영어",
            "fluency": "비즈니스 레벨"
        },
        {
            "language": "일본어",
            "fluency": "일상 회화 레벨"
        }
    ],
    "interests": [
        {
            "name": "개발",
            "keywords": ["웹", "오픈소스"]
        }
    ],
    "references": [
        {
            "name": "김철수",
            "reference": "Lorem ipsum dolor sit amet, consectetur adipiscing elit. 추천합니다."
        }
    ]
}
